ever_playground-0.7.7.dist-info/METADATA
ever_playground-0.7.7.dist-info/WHEEL
ever_playground-0.7.7.dist-info/license_files/LICENSE
ever_playground/__init__.py
ever_playground/ever_playground.pyi
ever_playground/ever_playground.cpython-310-x86_64-linux-gnu.so
ever_playground-0.7.7.dist-info/RECORD
