Metadata-Version: 2.1
Name: ever-playground
Version: 0.7.7
License-File: LICENSE
License: GPL-3.0-only
Requires-Python: >=3.7
